README.md
setup.py
git_repos.egg-info/PKG-INFO
git_repos.egg-info/SOURCES.txt
git_repos.egg-info/dependency_links.txt
git_repos.egg-info/entry_points.txt
git_repos.egg-info/requires.txt
git_repos.egg-info/top_level.txt
repos/__init__.py
repos/cli.py
repos/repo.py
repos/repos.py
repos/spinner.py
repos/ui.py